design.sv
// Code your design here
`timescale 1ns / 1ps
module fifo(
  input[7:0] data_in,
  input wr, rd, clk, rst,
  output reg[7:0] data_out,
  output reg empty, full,
  output reg[4:0] cnt
);
  
  reg[7:0] mem[15:0];
  reg[4:0] rd_ptr, wr_ptr;
  
  initial
    begin
      $dumpfile("dump.vcd");
      $dumpvars(1, fifo);
    end
  
  always @(*)
    begin
      if(rst) 
        begin
          rd_ptr <= 5'b00000;
          wr_ptr <= 5'b00000;
          empty <= 1'b1;
          full <= 1'b0;
          cnt <= 5'b00000;
        end
    end

  always @(negedge clk)
    begin
      if(rd && !empty)
        begin
          data_out = mem[rd_ptr];
          rd_ptr = rd_ptr + 5'b00001;
          cnt = cnt - 5'b00001;
          if (cnt==5'b00000)
            empty = 1'b1;
          else
            empty = 1'b0;
          
          if(cnt==5'b10000)
            full = 1'b1;
          else
            full = 1'b0;
        end
      else if(wr && !full)
        begin
          mem[wr_ptr] = data_in;
          wr_ptr = wr_ptr + 5'b00001;
          cnt = cnt + 5'b00001;
          if(cnt==5'b10000)
            full = 1'b1;
          else
            full = 1'b0;
          
          if (cnt==5'b00000)
            empty = 1'b1;
          else
            empty = 1'b0;
        end
      else
        $display("Error");
    end
endmodule

testbench.sv
// Code your testbench here
// or browse Examples
`timescale 1ns / 1ps
module tb;
  reg[7:0] ip;
  reg wr, rd, clk, rst;
  wire empty, full;
  wire[4:0] cnt;
  wire[7:0] op;
  
  fifo Fifo(
    ip,
    wr,rd,clk,rst,
    op,
    empty, full,
    cnt
  );
  
  integer i;
  
  always #10 clk <= ~clk;
  
  initial
    begin
      
      $monitor("Time = %0t clk = %0d ip = %0d wr = %0d rd = %0d rst = %0d op = %0d empty = %0d full = %0d cnt = %0d", $time, clk, ip, wr, rd, rst, op, empty, full, cnt);
      clk = 1'b1;
      rst = 1'b1;

      #20;
      rst = 1'b0;
      #10;
      wr = 1'b1;
      ip = 8'b00010001;
      rd = 1'b0;

      #20;
      wr = 1'b1;
      ip = 8'b00000110;
      rd = 1'b0;
      
      #20;
      wr = 1'b1;
      ip = 8'b01000011;
      rd = 1'b0;

      #20;
      wr = 1'b1;
      ip = 8'b00010100;
      rd = 1'b0;

      #20;
      wr = 1'b0;
      rd = 1'b1;

      #20;
      wr = 1'b0;
      rd = 1'b1;

      $finish;      
    end 
endmodule

dump.vcd
$date
	Sat Dec 26 16:16:29 2020
$end
$version
	Icarus Verilog
$end
$timescale
	1ps
$end
$scope module tb $end
$scope module Fifo $end
$var wire 1 ! clk $end
$var wire 8 " data_in [7:0] $end
$var wire 1 # rd $end
$var wire 1 $ rst $end
$var wire 1 % wr $end
$var reg 5 & cnt [4:0] $end
$var reg 8 ' data_out [7:0] $end
$var reg 1 ( empty $end
$var reg 1 ) full $end
$var reg 5 * rd_ptr [4:0] $end
$var reg 5 + wr_ptr [4:0] $end
$upscope $end
$upscope $end
$enddefinitions $end
#0
$dumpvars
b0 +
b0 *
0)
1(
bx '
b0 &
x%
1$
x#
bx "
1!
$end
#10000
0!
#20000
1!
0$
#30000
0(
b1 &
b1 +
0!
0#
b10001 "
1%
#40000
1!
#50000
b10 &
b10 +
0!
b110 "
#60000
1!
#70000
b11 &
b11 +
0!
b1000011 "
#80000
1!
#90000
b100 &
b100 +
0!
b10100 "
#100000
1!
#110000
b11 &
b1 *
b10001 '
0!
1#
0%
#120000
1!
#130000
b10 &
b10 *
b110 '
0!
